[
    {
       "author": "Almaca, C.",
       "year": 1959,
        "title": "Acção imobilizadora do formol a 5", 
        "pub": "Boletim da Sociedade Portuguesa de Ciencias Naturais",
        "locale": "7(3): 139-143"
    },
    {
        "author": "Almaca, C.",
        "year": 1959,
         "title": "Notas Anfibiologicas I.", 
         "pub": "Boletim da Sociedade Portuguesa de Ciencias Naturais",
         "locale": "7(3): 144-147"
     },
     {
        "author": "Almaca, C.",
        "year": 1959,
         "title": "Uma espécie que devemos proteger: a Chioglossa lusitanica Boc.", 
         "pub": "Boletim da Liga para a Proteccao da Natureza, Nova Serie",
         "locale": "1: 8-9"
     },
     {
        "author": "Almaca, C.",
        "year": 1959,
         "title": "Anfíbios portugueses. Apontamentos sobre a sua sistemática e ecologia.", 
         "pub": "Naturalia",
         "locale": "8(1): 47-52"
     },
     {
        "author": "Almaca, C.",
        "year": 1959,
         "title": "Sobre a variabilidade e a posição sistemática do Xantho incisus Leach [=X. floridus (Montagu)] da zona intercotidal do litoral português.", 
         "pub": "Revista da Faculdade de Ciências da Universidade de Lisboa, 2ª série, C",
         "locale": "7(2): 233-252"
     },
     {
        "author": "Almaca, C.",
        "year": 1959,
         "title": "Caranguejos da zona intercotidal da região de Caxias-Cabo Raso.", 
         "pub": "Naturalia",
         "locale": "8(1-2): 22-28"
     },
     {
        "author": "Almaca, C.",
        "year": 1960,
         "title": "Contribuição para o estudo da zonação marinha do litoral português.", 
         "pub": "Boletim da Sociedade Portuguesa de Ciencias Naturais",
         "locale": "8: 201-208"
     },
     {
        "author": "Almaca, C.",
        "year": 1961,
         "title": "Variabilidade de alguns caracteres usados na taxonomia do gén. Carcinus Leach.", 
         "pub": "Revista da Faculdade de Ciências da Universidade de Lisboa, 2ª série, C",
         "locale": "8(2): 137-153"
     },
     {
        "author": "Almaca, C.",
        "year": 1961,
         "title": "Notas sobre o Xantho incisus Leach de Parede, Portugal.", 
         "pub": "Revista da Faculdade de Ciências da Universidade de Lisboa, 2ª série, C",
         "locale": "8(2): 155-165"
     },
     {
        "author": "Almaca, C.",
        "year": 1962,
         "title": "Sur la distribution geographique du genre Carcinus Leach (Crust. Dec. Brach.).", 
         "pub": "Revista da Faculdade de Ciências da Universidade de Lisboa, 2ª série, C",
         "locale": "10: 109-113"
     },
     {
        "author": "Almaca, C.",
        "year": 1962,
         "title": "Sobre a distribuição de Aeolidia pappilosa (Linné) (Mol. Gast. Opist.).", 
         "pub": "Boletim da Sociedade Portuguesa de Ciências Naturais, 2ª série",
         "locale": "8: 209-211"
     },
     {
        "author": "Almaca, C.",
        "year": 1963,
         "title": "Sur le probléme de l’origine de Carcinus maenas (L.) du littoral américain.", 
         "pub": "Revista da Faculdade de Ciências de Lisboa, 2ª série, C",
         "locale": "11(2): 119-136"
     },
     {
        "author": "Almaca, C.",
        "year": 1963,
         "title": "Sur les crabes du genre Xantho Leach, 1815, du Museum Zoologique de l’Université de Coimbra.", 
         "pub": "Memórias e Estudos do Museu Zoológico da Universidade de Coimbra,",
         "locale": "281: 1-9"
     },
     {
        "author": "Almaca, C.",
        "year": 1963,
         "title": "Sobre o habitat e a abundância de Pirimela denticulata (Montagu, 1808) (Crust. Dec. Brach.).", 
         "pub": "Boletim da Sociedade Portuguesa de Ciências Naturais, 2ª série,",
         "locale": "9: 166-169"
     },
     {
        "author": "Almaca, C.",
        "year": 1963,
         "title": "Sur un cyprinide nouveau pour le Portugal: Chondrostoma toxostoma toxostoma (Vallot), 1836.", 
         "pub": "Boletim da Sociedade Portuguesa de Ciências Naturais, 2ª série,",
         "locale": "10: 63-65"
     },
     {
        "author": "Almaca, C.",
        "year": 1963,
         "title": "Varia.", 
         "pub": "Naturalia,",
         "locale": "8: 1-2"
     },
     {
        "author": "Almaca, C.",
        "year": 1964,
         "title": "A fauna herpetológica da Serra do Gerês.", 
         "pub": "Naturalia,",
         "locale": "9(1-2): 62-65"
     },
     {
        "author": "Almaca, C.",
        "year": 1964,
         "title": "A zona das marés, seu interesse no ensino da zoologia.", 
         "pub": "Naturalia,",
         "locale": "9(1-2): 1-3"
     },
     {
        "author": "Almaca, C.",
        "year": 1964,
         "title": "Deux notes sur les mammifères ibériques.", 
         "pub": "Anais da Faculdade de Ciências do Porto,",
         "locale": "47: 1-10"
     },
     {
        "author": "Almaca, C.",
        "year": 1964,
         "title": "Deux notes sur les mammifères ibériques.", 
         "pub": "Publicações do Instituto de Zoologia “Dr. Augusto Nobre”, Faculdade de Ciências do Porto,",
         "locale": "92: 1-6"
     },
     {
        "author": "Almaca, C.",
        "year": 1964,
         "title": "Contribuição para o conhecimento da fauna ictiológica das águas interiores portuguesas.", 
         "pub": " Boletim da Sociedade Portuguesa de Ciências Naturais, 2ª série,",
         "locale": "10: 228-237"
     },
     {
        "author": "Almaca, C.",
        "year": 1965,
         "title": "Contribution à la connaissance des poissons des eaux intérieures du Portugal.", 
         "pub": " Boletim da Sociedade Portuguesa de Ciências Naturais,",
         "locale": "10: 225-263"
     },
     {
        "author": "Almaca, C.",
        "year": 1965,
         "title": "Contribution à la connaissance des poissons des eaux intérieures du Portugal.", 
         "pub": " Arquivos do Museu Bocage (2ª série),",
         "locale": "1(2): 9-39"
     },
     {
        "author": "Almaca, C.",
        "year": 1965,
         "title": "Contribution à la connaissance des poissons des eaux intérieures du Portugal.", 
         "pub": " Revista da Faculdade de Ciências de Lisboa, 2ª série, C,",
         "locale": "13(2): 225-262"
     },
     {
        "author": "Almaca, C.",
        "year": 1965,
         "title": "Notícias bibliográficas. The ecology of rocky shores, por J.R. Lewis.", 
         "pub": " Revista da Faculdade de Ciências de Lisboa, 2ª série, C,",
         "locale": "13(2): 274-275"
     },
     {
        "author": "Almaca, C.",
        "year": 1965,
         "title": "Alguns aspectos da conservação da fauna aquática nas regiões beiroas.", 
         "pub": " Arquivo Coimbrão,",
         "locale": "21-22: 377-379"
     },
     {
        "author": "Almaca, C.",
        "year": 1965,
         "title": "Deuxième capture des poissons Trachypterus arcticus (Brunnich, 1788) et Cyclopterus lumpus L., 1758 au Portugal.", 
         "pub": "Arquivos do Museu Bocage, I, Notas e Suplementos,",
         "locale": "2: 1-2"
     },
     {
        "author": "Almaca, C.",
        "year": 1966,
         "title": "Sur la systématique des barbeaux marocains (Pisces, Cyprinidae, Barbus).", 
         "pub": "Arquivos do Museu Bocage, (2ª série),",
         "locale": "1(7): 111-121"
     },
     {
        "author": "Almaca, C.",
        "year": 1966,
         "title": "Nouvelles observations sur Rhinolophus mehelyi Matschie, 1901, au Portugal.", 
         "pub": "Arquivos do Museu Bocage, (2ª série), Notas e Suplementos,",
         "locale": "1(8): 1-4"
     },
     {
        "author": "Almaca, C.",
        "year": 1966,
         "title": "Publicações do Prof. Dr. Augusto Nobre sobre oceanografia biológica.", 
         "pub": "Boletim da Sociedade Portuguesa de Ciências Naturais, 2ª série,",
         "locale": "11: 15-25"
     },
     {
        "author": "Almaca, C.",
        "year": 1967,
         "title": "Estudo das populações portuguesas do gén. Barbus Cuvier, 1817 (Pisces, Cyprinidae).", 
         "pub": "Tese de doutoramento em Biologia, Universidade de Lisboa, Lisboa,",
         "locale": "255 pp."
     },
     {
        "author": "Almaca, C.",
        "year": 1967,
         "title": "Estudo das populações portuguesas do gén. Barbus Cuvier, 1817 (Pisces, Cyprinidae).", 
         "pub": "Revista da Faculdade de Ciências de Lisboa, 2ª série, C,",
         "locale": "14(2): 151-400"
     },
     {
        "author": "Almaca, C.",
        "year": 1967,
         "title": "Sur la position taxonomique de Pitymys lusitanicus (Gerbe) (Mammalia, Rodentia).", 
         "pub": "Arquivos do Museu Bocage,",
         "locale": "1(13): 249-256"
     },
     {
        "author": "Almaca, C.",
        "year": 1967,
         "title": "Introdução ao estudo cuantitativo das populações animais.", 
         "pub": "Naturalia",
         "locale": "9(3-4): 1-24"
     },
     {
        "author": "Almaca, C.",
        "year": 1967,
         "title": "Elementos para o estudo ecológico da zona intercotidal rocosa do litoral português.", 
         "pub": "Lisboa",
         "locale": "41 pp."
     },
     {
        "author": "Almaca, C.",
        "year": 1968,
         "title": "Os peixes de água doce e a Zoogeografia da Península Ibérica.", 
         "pub": "Actualidades Biológicas, Lisboa,",
         "locale": "40: 125-148"
     },
     {
        "author": "Almaca, C.",
        "year": 1968,
         "title": "Révision critique de quelques types de cyprinidés d’Europe et d’Afrique du Nord des collections du Muséum National d’Histoire Naturelle.", 
         "pub": "Bulletin du Muséum National d’Histoire Naturelle, Paris, 2ª série,",
         "locale": "40(6): 1116-1144"
     },
     {
        "author": "Almaca, C.",
        "year": 1968,
         "title": "A peculiaridade da fauna ibérica (vertebrados terrestres).", 
         "pub": "Revista da Faculdade de Ciências de Lisboa, 2ª série, C,",
         "locale": "15(2): 209-231"
     },
     {
        "author": "Almaca, C.",
        "year": 1968,
         "title": "La faune mammalogique du Portugal dans la “Checklist of Palearctic and Indian Mammals”,          1951, par Ellerman et Morrison-Scott.", 
         "pub": "Arquivos do Museu Bocage, II, Notas e Suplementos,",
         "locale": "12: 5-9"
     },
     {
        "author": "Almaca, C.",
        "year": 1969,
         "title": "Sur l’abondance relative des Cyprinidés du Portugal.", 
         "pub": "Arquivos do Museu Bocage, (2ª série),",
         "locale": "2(7): 83-98"
     },
     {
        "author": "Almaca, C.",
        "year": 1970,
         "title": "Sur les Barbeaux (genre et sousgenre Barbus) de l’Afrique du Nord.", 
         "pub": "Bulletin du Muséum National d’Histoire Naturelle, Paris, 2ª série,",
         "locale": "42(1): 141-158"
     },
     {
        "author": "Almaca, C.",
        "year": 1970,
         "title": "A herpetofauna da Serra do Gerês.", 
         "pub": "Proteção da Natureza. Nova Série,",
         "locale": "11:26"
     },
     {
        "author": "Almaca, C.",
        "year": 1970,
         "title": "Aspectos elementares da dinâmica das populações animais.", 
         "pub": "Naturalia",
         "locale": "10(1): 1-12"
     },
     {
        "author": "Almaca, C.",
        "year": 1970,
         "title": "ur un Cyprinidé nord-africain: Barbus issenensis ou Varicorhinus issenensis?", 
         "pub": "Bulletin du Muséum National d’Histoire Naturelle, Paris, 2e série,",
         "locale": "42(1): 159-160"
     },
     {
        "author": "Almaca, C.",
        "year": 1970,
         "title": "Essai d’application de critères biométriques dans la systématique des Pitymys ouesteuropéens. Distinction entre les groupes savii et duodecimcostatus.", 
         "pub": "Arquivos do Museu Bocage (2ª série),",
         "locale": "2(12): 149-171"
     },
     {
        "author": "Almaca, C.",
        "year": 1970,
         "title": "La position systématique des “petits” Pitymys ibériques d’après quelques critères biométriques.", 
         "pub": "Arquivos do Museu Bocage (2ª série),",
         "locale": "2(13): 173-180"
     },
     {
        "author": "Almaca, C.",
        "year": 1971,
         "title": "Sur la spéciation des barbeaux nord-africains.", 
         "pub": "Bulletin du Muséum National d’Histoire Naturelle, Paris, 2ª série,",
         "locale": "42(5): 853-856"
     },
     {
        "author": "Almaca, C.",
        "year": 1971,
         "title": "Sur la collection de Barbeaux (genre et sous-genre Barbus) ibériques et nord-africains du Forschungsinstitut Senckenberg (Frankfurt a.M.).", 
         "pub": "Arquivos do Museu Bocage (2ª série), 3, Notas e suplementos,",
         "locale": "21: 1-5"
     },
     {
        "author": "Almaca, C.",
        "year": 1971,
         "title": "Le caractère particulier de la faune ibérique (Vertébrés terrestres).", 
         "pub": "Bonner Zoologische Beiträge,",
         "locale": "22: 90-100"
     },
     {
        "author": "Almaca, C.",
        "year": 1971,
         "title": "A evolução dos Hominídeos.", 
         "pub": "Natura, Nova Série,",
         "locale": "1: 1-32"
     },
     {
        "author": "Almaca, C.",
        "year": 1971,
         "title": "Conservação da natureza e populações animais.", 
         "pub": "Direcção Geral dos Serviços Florestais e Aquícolas, Secretaria de Estado da Agricultura. Estudos e Divulgação Técnica, grupo A, Secção Protecção da Natureza. Lisboa:",
         "locale": "5-37"
     },
     {
        "author": "Almaca, C.",
        "year": 1971,
         "title": "Recherches biométriques sur les Pitymys des groupes savii et duodecimcostatus.", 
         "pub": "Revista de Biologia,",
         "locale": "7(3-4): 247-260"
     },
     {
        "author": "Almaca, C.",
        "year": 1972,
         "title": "Sur la systématique des Barbeaux (genre et sous-genre Barbus) de la Penínsule Ibérique et de l’Afrique du Nord.", 
         "pub": "Arquivos do Museu Bocage (2ª série),",
         "locale": "3(10): 319-346"
     },
     {
        "author": "Almaca, C.",
        "year": 1972,
         "title": "Note préliminaire sur les rapports entre quelques dimensions de la carapace de Carcinus maenas (L.) et C. mediterraneus Czerniavsky.", 
         "pub": "Thalassia Jugoslavica,",
         "locale": "8(1): 49-57"
     },
     {
        "author": "Almaca, C.",
        "year": 1972,
         "title": " Cetraria e zoologia.", 
         "pub": "A Fauna, Publicações Alfa, Lisboa,",
         "locale": "91-93: 1-11"
     },
     {
        "author": "Almaca, C.",
        "year": 1972,
         "title": "Elementos sobre a actividade sazonária dos répteis e anfíbios do Parque Nacional da Peneda-Gerês.", 
         "pub": " Publicações da Liga para a Protecção da Natureza, Lisboa,",
         "locale": "22: 1-15"
     },
     {
        "author": "Almaca, C.",
        "year": 1972,
         "title": "Elementos para o estudo ecológico da zona intercotidal rocosa do litoral português.", 
         "pub": " 2ª ed. Lisboa.",
         "locale": "41 pp."
     },
     {
        "author": "Almaca, C.",
        "year": 1973,
         "title": "Os tipos do grupo-espécie em zoologia.", 
         "pub": "Naturalia",
         "locale": "11(1): 73-75"
     },
     {
        "author": "Almaca, C.",
        "year": 1973,
         "title": "A poluição térmica: efeitos sobre os peixes e outros animais aquáticos.", 
         "pub": "Direcção Geral dos Serviços Florestais e Aquícolas, Secretaria de Estado da Agricultura. Estudos e divulgação Técnica, grupo A, Secção Protecção da Natureza. Lisboa:",
         "locale": "35 pp."
     },
     {
        "author": "Almaca, C.",
        "year": 1973,
         "title": "La distinction entre Pitymys lusitanicus (Gerbe) et P. duodecimcostatus (de Selys-Longchamps) d’aprés quelques indices craniometriques.", 
         "pub": "Revista de Biologia,",
         "locale": "9(1-4): 207-216"
     },
     {
        "author": "Almaca, C.",
        "year": 1973,
         "title": "Alguns comentários a estudos sobre a Zoologia de “Os Lusíadas”.", 
         "pub": "Actas I Reunião Internacional Camonistas, Lisboa:",
         "locale": "1-10"
     },
     {
        "author": "Almaca, C.",
        "year": 1973,
         "title": "Variabilidade genética e conservação das populações animais.", 
         "pub": "Protecção da Natureza,",
         "locale": "14: 19-23"
     },
     {
        "author": "Almaca, C.",
        "year": 1973,
         "title": "Sur la structure des populations des Pitymys Ibériques.", 
         "pub": "Revista da Faculdade de Ciências de Lisboa, 2ª série, C,",
         "locale": "17(2): 383-426"
     },
     {
        "author": "Almaca, C.",
        "year": 1973,
         "title": "A conservação da Praia das Avencas (Parede). Importância. Factores de degradação e sua eventual minimização.", 
         "pub": "Protecção da Natureza,",
         "locale": "14: 10-13"
     },
     {
        "author": "Almaca, C.",
        "year": 1974,
         "title": "Caracters craniometriques permettant la distinction entre P. savii pyrenaicus de Selys-Longchamps et les Pitymys iberiques, P. lusitanicus (Gerbe) et P. duodecimcostatus (de Selys-Long-champs).", 
         "pub": "Estudos sobre a Fauna Portuguesa, Faculdade de Ciências de Lisboa,",
         "locale": "4: 1-16"
     },
     {
        "author": "Almaca, C.",
        "year": 1974,
         "title": "Nouvelle méthode biométrique confirmant la spéciation dans les deux groupes de Pitymys ibériques.", 
         "pub": "Comptes Rendus Hebdomadaires des Seances de l’Academie des Sciences de Paris, série D,",
         "locale": "278(4): 477-480"
     },
     {
        "author": "Almaca, C.",
        "year": 1974,
         "title": "Conservação e Ecologia.", 
         "pub": "A Fauna, Publicações Alfa, Lisboa,",
         "locale": "151-165: 1-32"
     },
     {
        "author": "Almaca, C.",
        "year": 1974,
         "title": "Parque Nacional da Peneda-Gerês. Anfíbios e Répteis.", 
         "pub": "Gazeta Mobil, Lisboa,",
         "locale": "188: 1-5"
     },
     {
        "author": "Almaca, C.",
        "year": 1975,
         "title": "Comparaison de peuplements intertidaux de Brachyura et Porcellanidae en deux plages rocheuses du Portugal.", 
         "pub": "Estudos sobre a Fauna Portuguesa, Faculdade de Ciências de Lisboa,",
         "locale": "6: 1-15"
     },
     {
        "author": "Almaca, C.",
        "year": 1975,
         "title": "Sur l’écologie comparée de peuplements intertidaux de Brachyura et Porcellanidae.", 
         "pub": "Estudos sobre a Fauna Portuguesa, Faculdade de Ciências de Lisboa,",
         "locale": "9: 1-14"
     },
     {
        "author": "Almaca, C.",
        "year": 1975,
         "title": "Museus de Zoologia e estratégia da investigação zoológica. Actas do Coloquio: Museus Para Quê?", 
         "pub": "Associação Portuguesa de Museologia (APOM). Neogravura. Lisboa:",
         "locale": "61-72"
     },
     {
        "author": "Almaca, C.",
        "year": 1975,
         "title": "Normes légales sur la protection des mammifères sauvages au Portugal.", 
         "pub": "Actas do XII Congresso da União Internacional dos Biologistas da Caça, Direção Geral dos Recursos  Florestais, Serviço de Inspecção da Caça e Pesca, Lisboa:",
         "locale": "319-320"
     },
     {
        "author": "Almaca, C.",
        "year": 1976,
         "title": "La spéciation chez les Cyprinidae de la Péninsule Ibérique.", 
         "pub": "Revue des Travaux de l’Institut des Pêches Maritimes,",
         "locale": "40(3-4): 399-411"
     },
     {
        "author": "Almaca, C.",
        "year": 1976,
         "title": "Zoogeografia e especiação dos Ciprinídeos da Península Ibérica.", 
         "pub": "Natura, Nova Série,",
         "locale": "4: 1-28"
     },
     {
        "author": "Almaca, C.",
        "year": 1976,
         "title": "Les zoos et la conservation de populations d’espéces menacées: quelques aspects généticoévolutifs et écologiques.", 
         "pub": "Boletim da Sociedade Portuguesa de Ciências Naturais,",
         "locale": "16: 65-70"
     },
     {
        "author": "ALMAÇA, C., COLLARES-PEREIRA, M.J., CRESPO, E.G., MAGALHAES, C. & MASCARENHAS, M.J.,",
        "year": 1976,
         "title": "Sur l’écologie des reptiles et amphibiens du Parc National de Peneda-Gerês.", 
         "pub": "Boletim da Sociedade Portuguesa de Ciências Naturais,",
         "locale": "16: 5-19"
     },
     {
        "author": "Almaca, C.",
        "year": 1977,
         "title": "Quelques aspects de la dynamique des populations de Brachyoures et Porcellanides intertidaux.", 
         "pub": "Boletim da Sociedade Portuguesa de Ciências Naturais,",
         "locale": "17: 79-89"
     },
     {
        "author": "Almaca, C.",
        "year": 1977,
         "title": "As colheitas com fins didácticos e científicos e a conservação das zonas intercotidais rochosas: o caso da Praia das Avencas-Parede.", 
         "pub": "Publicações da Liga para a Protecção da Natureza, Lisboa,",
         "locale": "23: 13-18"
     },
     {
        "author": "Almaca, C.",
        "year": 1977,
         "title": "Sur les types nord-africains de Pseudophoxinus Bleeker, 1860 du Museum d’Histoie Naturelle de Paris.", 
         "pub": "Cybium, 3ª série,",
         "locale": "2: 25-33"
     },
     {
        "author": "Almaca, C.",
        "year": 1977,
         "title": "Conservação da natureza e turismo. Reflexões sobre o Parque Nacional da Peneda-Gerês.", 
         "pub": "Natureza e Paisagem,",
         "locale": "3: 51-63"
     },
     {
        "author": "Almaca, C.",
        "year": 1978,
         "title": "Répartition géographique des Cyprinidae ibériques et secteurs ichthyogéographiques de la Péninsule Ibérique.", 
         "pub": "Vestnik Ceskoslovenské Spolecnosti Zoologické,",
         "locale": "42(4): 241-248"
     },
     {
        "author": "Almaca, C.",
        "year": 1978,
         "title": "Spéciation et subspéciation chez les Cyprinidae ibériques et nord-africains.", 
         "pub": "Bulletin de l’Office National des Pêches de Tunisie,",
         "locale": "2(1-2): 23-30"
     },
     {
        "author": "Almaca, C.",
        "year": 1978,
         "title": "Guia para uma excursão à Serra de Sintra. Anfíbios.", 
         "pub": "Arquivos do Museu Bocage, sér. ECE (Extensão Cultural e Ensino),",
         "locale": "14: 1-7"
     },
     {
        "author": "Almaca, C.",
        "year": 1978,
         "title": "Guia para uma excursão à Serra de Sintra. Anfíbios.", 
         "pub": "Arquivos do Museu Bocage, sér. ECE (Extensão Cultural e Ensino),",
         "locale": "Adenda ao número 14"
     },
     {
        "author": "Almaca, C.",
        "year": 1978,
         "title": "Ecologie humaine et conservation de la nature.", 
         "pub": "Boletim da Sociedade Portuguesa de Ciências Naturais,",
         "locale": "18: 91-92"
     },
     {
        "author": "Almaca, C.",
        "year": 1979,
         "title": "La notion de “population” et la Systématique Zoologique.", 
         "pub": "Revue Roumaine de Biologie, Série de Biologie Animale,",
         "locale": "24(1): 15-17"
     },
     {
        "author": "Almaca, C.",
        "year": 1979,
         "title": "Les espèces et la spéciation chez les Pseudophoxinus nord-africains (Pisces, Cyprinidae).", 
         "pub": "Bulletin du Muséum National d’Histoire Naturelle, Paris, 4e série, 1, section A,",
         "locale": "1: 279-284"
     },
     {
        "author": "Almaca, C.",
        "year": 1979,
         "title": "Conservação dos vertebrados portugueses. Os anfíbios.", 
         "pub": "Boletim da Comissão Nacional do Ambiente,",
         "locale": "5(7-8) - Anexo, 2 pp."
     },
     {
        "author": "Almaca, C.",
        "year": 1979,
         "title": "Conservação dos vertebrados portugueses. Os Ciprinídeos.", 
         "pub": "Boletim da Comissão Nacional do Ambiente,",
         "locale": "5(9-10) - Anexo, 2 pp."
     },
     {
        "author": "Almaca, C.",
        "year": 1979,
         "title": "Ciências Naturais. Biologia.", 
         "pub": "Ministério da Educação, Lisboa,",
         "locale": "87 pp"
     },
     {
        "author": "Almaca, C.",
        "year": 1979,
         "title": "Inventariação de recursos: cooperação de Portugal nas iniciativas da ESF.", 
         "pub": "Actas do Simpósio Nacional de Ciência e Tecnologia para o desenvolvimento (SINACT). Lisboa:",
         "locale": "3 pp"
     },
     {
        "author": "CAETANO, M.H., COELHO, M.M., ALMAÇA, C. & COLLARES-PEREIRA, M.J.,",
        "year": 1979,
         "title": "Notes sur l’écologie des amphibiens et reptiles du Parc National de Peneda-Gerês (Portugal).", 
         "pub": "Arquivos do Museu Bocage (2ª série),",
         "locale": "7(2): 9-22"
     },
     {
        "author": "COLLARES-PEREIRA, M.J. & ALMAÇA, C.",
        "year": 1979,
         "title": "Pseudophoxinus hispanicus (Steindachner, 1866), Cyprinidae nouveau pour le Portugal.", 
         "pub": "Bulletin du Muséum National d’Histoire Naturelle, Paris, 4e série, 1, section A,",
         "locale": "1: 285-287"
     },
     {
        "author": "Almaca, C.",
        "year": 1980,
         "title": "Introdução de espécies animais. Seus condicionalismos genéticos e ecológicos.", 
         "pub": "Giesta",
         "locale": "2: 1-7"
     },
     {
        "author": "Almaca, C.",
        "year": 1980,
         "title": "A conservação da Praia das Avencas (Parede). Importância. Factores de degradação e sua eventual minimização.", 
         "pub": "Conservação da Natureza, M.E.C.",
         "locale": "131-139"
     },
     {
        "author": "Almaca, C.",
        "year": 1981,
         "title": "La collection de Barbus d’Europe du Muséum national d’Histoire naturelle (Cyprinidae, Pisces).", 
         "pub": "Bulletin du Muséum National d’Histoire Naturelle, Paris, 4e série, 3, section A,",
         "locale": "1: 277-307"
     },
     {
        "author": "Almaca, C.",
        "year": 1981,
         "title": "Apport de la dynamique des populations aquatiques à la génétique évolutive. In: Dynamique de populations et qualité de l’eau.", 
         "pub": "Ed. Bordas, Dunod, Gauthier-Villars. Paris: ",
         "locale": "257-272"
     },
     {
        "author": "Almaca, C.",
        "year": 1981,
         "title": "Formas de especiação nos animais.", 
         "pub": "Arquipélago (série Ciências da Natureza),",
         "locale": "2: 7-35"
     },
     {
        "author": "Almaca, C.",
        "year": 1981,
         "title": "Subespécies e subespeciação.", 
         "pub": "Arquipélago (série Ciências da Natureza),",
         "locale": "2: 37-57"
     },
     {
        "author": "Almaca, C.",
        "year": 1982,
         "title": "A conservação da fauna no âmbito de um plano de ordenamento biofísico do Algarve.", 
         "pub": "Actas do 2º Congresso Nacional sobre o Algarve. Junta Nacional de Investigação Científica e Tecnológica. Balaia:",
         "locale": " 253-257"
     },
     {
        "author": "Almaca, C.",
        "year": 1982,
         "title": "Evolutionary and conservationist implications of man-made discontinuities in ecosystems.", 
         "pub": "In: V.J.A. Novák & J. Mlíkovsky (eds.). Evolution and Environment. 2. Proceedings of the International Symposium, Brno 1981. Praga:",
         "locale": "999-1008"
     },
     {
        "author": "Almaca, C.",
        "year": 1982,
         "title": "Re-examination of the types of Barbus haasi Mertens, 1924 (Pisces: Cyprinidae).", 
         "pub": "Senckenbergiana Biologica,",
         "locale": "63(1-2): 33-38"
     },
     {
        "author": "Almaca, C.",
        "year": 1982,
         "title": "Marine slides and allopatric speciation. slides and other mass movements. ", 
         "pub": "NATO Conference Series, IV, Marine Sciences. Plenum Press. New York:",
         "locale": "325-334"
     },
     {
        "author": "Almaca, C.",
        "year": 1982,
         "title": "Que futuro para o Museu Bocage?", 
         "pub": "Actas do Coloquio: Museus Universitários, Sua Inserção Activa na Cultura Portuguesa. APOM. Lisboa.",
         "locale": ""
    },
    {
        "author": "Almaca, C.",
        "year": 1982,
         "title": "Note sur la biologie des populations de Carcinus maenas (L.) de la zone intertidale du Portugal occidental.", 
         "pub": "Quaderni del Laboratório di Tecnologia della Pesca,",
         "locale": "3(2-5): 179-185"
    },
    {
        "author": "GIL, F.B. & ALMAÇA, C.",
        "year": 1982,
         "title": "Os museus de região e o desenvolvimento científico.", 
         "pub": "Actas do Colóquio APOM 77, Ponta Delgada (Açores). APOM. Lisboa:",
         "locale": "35-44"
    },
    {
        "author": "Almaca, C.",
        "year": 1983,
         "title": "Iberian and Mediterranean elements in the Iberian fauna of Barbus.", 
         "pub": "Senckenbergiana Biologica,",
         "locale": "63(5-6): 329-332"
    },
    {
        "author": "Almaca, C.",
        "year": 1983,
         "title": "Recursos faunísticos do Algarve. Papel da Universidade na inventariação e conservação desse recursos num plano de desenvolvimento regional.", 
         "pub": "In: O papel da universidade no processo de regionalização e de desenvolvimento regional. Universidade do Algarve. Faro:",
         "locale": "203-215"
    },
    {
        "author": "Almaca, C.",
        "year": 1983,
         "title": "Notes on Barbus graellsii Steindachner, 1866.", 
         "pub": "Annalen des Naturhistorischen Museums in Wien, B,",
         "locale": "85: 1-7"
    },
    {
        "author": "Almaca, C.",
        "year": 1983,
         "title": "Remarks on some Heckel’s species of Barbus from western Asia.", 
         "pub": "Arquivos do Museu Bocage (série B),",
         "locale": "2(12): 95-102"
    },
    {
        "author": "Almaca, C.",
        "year": 1983,
         "title": "Contemporary changes in Portuguese freshwater fish fauna and conservation of autochthonous Cyprinidae.", 
         "pub": "Roczniki Nauk Rolniczych, Seria H.T.,",
         "locale": "100(3): 9-15"
    },
    {
        "author": "Almaca, C.",
        "year": 1983,
         "title": "Espécie e subespécie em paleoantropologia.", 
         "pub": "Garcia de Orta, série de Antropologia, Lisboa,",
         "locale": "2(1-2): 3-8"
    },
    {
        "author": "Almaca, C.",
        "year": 1984,
         "title": "Form relationships among Western Palearctic species of Barbus (Cyprinidae, Pisces).", 
         "pub": "Arquivos do Museu Bocage (série A),",
         "locale": "2(12): 207-248"
    },
    {
        "author": "Almaca, C.",
        "year": 1984,
         "title": "Notes on some species of Western Palearctic Barbus (Cyprinidae, Pisces).", 
         "pub": "Arquivos do Museu Bocage (série C Suplementos),",
         "locale": " 2(1): 1-76"
    },
    {
        "author": "Almaca, C.",
        "year": 1984,
         "title": "Alguns aspectos biológicos da hominização.", 
         "pub": "Arquipélago, Série Ciências da Natureza,",
         "locale": "5: 9-23"
    },
    {
        "author": "Almaca, C.",
        "year": 1984,
         "title": "Conservação das zonas ribeirinhas.", 
         "pub": "Boletim para a Protecção da Natureza, 3ª série,",
         "locale": "18: 13-19"
    },
    {
        "author": "Almaca, C.",
        "year": 1985,
         "title": "Evolutionary and zoogeographical remarks on the Mediterranean fauna of Brachyuran crabs.", 
         "pub": "NATO Conference Series, I, Ecology,",
         "locale": "8: 347-366"
    },
    {
        "author": "Almaca, C.",
        "year": 1985,
         "title": "Considerações zoogeográficas sobre a fauna ibérica de Brachyura (Decapoda, Crustacea).", 
         "pub": "Arquivos do Museu Bocage (série A),",
         "locale": "3(4): 51-68"
    },
    {
        "author": "Almaca, C.",
        "year": 1985,
         "title": "Morphological relationship and evolutionary rate of taxonomic characters in Euro-Mediterranean Barbus (Cyprinidae, Pisces).", 
         "pub": "Arquivos do Museu Bocage (série B),",
         "locale": "2(16): 129-136"
    },
    {
        "author": "Almaca, C.",
        "year": 1985,
         "title": "A ictiofauna continental alentejana na exploração zoológica do Dr. Franz Steindachner à Península Ibérica (1864-1865).", 
         "pub": "Congresso sobre o Alentejo, Évora,",
         "locale": "2: 532-536"
    },
    {
        "author": "Almaca, C.",
        "year": 1985,
         "title": "Sobre alguns migradores antibióticos da bacia do Guadiana.", 
         "pub": "Actas do II Congresso sobre o Alentejo, Évora,",
         "locale": " 2: 546-552"
    },
    {
        "author": "Almaca, C.",
        "year": 1985,
         "title": "Museos de zoologia e investigação científica.", 
         "pub": "Cadernos de Museologia, 2. Suplemento ao Boletim APOM Informações. Associação Portuguesa de Museologia, Lisboa.",
         "locale": "32 pp"
    },
    {
        "author": "Almaca, C.",
        "year": 1985,
         "title": "Espécie e subespécie em paleoantropologia.", 
         "pub": "Arquivo de Anatomia e Antropologia,",
         "locale": "39: 191-200"
    },
    {
        "author": "Almaca, C.",
        "year": 1985,
         "title": "Problems ecológicos relacionados com o empreendimento de Alqueva: a transformação da fácies lótica em fácies lêntica.", 
         "pub": "In: Actas do II Encontro “Prosseguir Alqueva para desenvolver o Alentejo e o País”. Edições Caminho. Setúbal:",
         "locale": "185-188"
    },
    {
        "author": "Almaca, C.",
        "year": 1986,
         "title": "On some Barbus species from Western Asia (Cyprinidae, Pisces).", 
         "pub": "Annalen des Naturhistorischen Museums in Wien, B,",
         "locale": "87: 5-30"
    },
    {
        "author": "Almaca, C.",
        "year": 1986,
         "title": "Homenagem ao Prof. António de Almeida.", 
         "pub": "Boletim da Sociedade de Geografia de Lisboa, série 104,",
         "locale": "1-6: 5-8"
    },
    {
        "author": "Almaca, C.",
        "year": 1987,
         "title": "A Zoologia e a Antropologia na Escola Politécnica e na Faculdade de Ciências da Universidade de Lisboa (até 1983).", 
         "pub": "In: F.B. Gil & M.G. Canelhas (eds.). Faculdade de Ciências da Universidade de Lisboa. Passado, presente, perspectivas futuras. Exposição comemorativa do 150º aniversário da Escola Politécnica e do 75º aniversário da Faculdade de Ciências da Universidade de Lisboa. Catálogo. Museu de Ciência, Lisboa:",
         "locale": "293-312"
    },
    {
        "author": "Almaca, C.",
        "year": 1987,
         "title": "Egg number and size in Pachygrapsus maurus (Lucas, 1846) from Praia da Laginha (Faial, Azores islands).", 
         "pub": "Investigación Pesquera, 51(Suplemento 1):",
         "locale": "157-163"
    },
    {
        "author": "Almaca, C.",
        "year": 1987,
         "title": "On the Portuguese populations of Austropotamobius pallipes (Lereboullet, 1858).", 
         "pub": "Investigación Pesquera, 51(Suplemento 1):",
         "locale": "403-411"
    },
    {
        "author": "Almaca, C.",
        "year": 1987,
         "title": "Crabs of the Sabellaria alveolata (Linnaeus, 1767) community: Egg number and population size structure in Pilumnus hirtellus (Linnaeus, 1761) and Porcellana platycheles (Pennant, 1777).", 
         "pub": "Arquivos do Museu Bocage, Nova Série, 1(3):",
         "locale": "19-32"
    },
    {
        "author": "Almaca, C.",
        "year": 1987,
         "title": "The Museu Bocage and the new series of its Arquives.", 
         "pub": "Arquivos do Museu Bocage, Nova Série, 1(1):",
         "locale": "1-8"
    },
    {
        "author": "Almaca, C.",
        "year": 1988,
         "title": "On the sturgeon, Acipenser sturio, in the Portuguese rivers and sea.", 
         "pub": "Folia Zoologica,",
         "locale": "37(2): 183-191"
    },
    {
        "author": "Almaca, C.",
        "year": 1988,
         "title": "Remarks on the biogeography of Euro-Mediterranean Barbus (Cyprinidae, Pisces).", 
         "pub": "Bulletin d’Ecologie,",
         "locale": "19(2-3): 159-162"
    },
    {
        "author": "Almaca, C.",
        "year": 1988,
         "title": "Compte Rendu de la Table Ronde: Les Poissons des Îles de la Méditerranée Occidentale (Baléares, Corse, Sardaigne, Sicile).", 
         "pub": "Bulletin d’Ecologie,",
         "locale": "19(2-3): 471-472"
    },
    {
        "author": "Almaca, C.",
        "year": 1988,
         "title": "Fish and their environment in large European river ecosystems: Tejo and Guadiana.", 
         "pub": "Sciences de l’Eau,",
         "locale": "7(1): 3-19"
    },
    {
        "author": "Almaca, C.",
        "year": 1988,
         "title": "As reservas naturais.", 
         "pub": "Fundação Calouste Gulbenkian. Lisboa:",
         "locale": "29-42"
    },
    {
        "author": "Almaca, C.",
        "year": 1988,
         "title": "Buffon, Lamarck, and the origin of man.", 
         "pub": "Proceedings of the 5th Congress of the European Anthro-pological Association, Lisboa,",
         "locale": "1"
    },
    {
        "author": "ALMAÇA, C. & COLLARES-PEREIRA, M.J.",
        "year": 1988,
         "title": "On the occurrence of the European river lamprey, Lampetra fluviatilis (Linnaeus, 1758), in the  Iberian Peninsula.", 
         "pub": "Cybium,",
         "locale": "12(1): 9-15"
    },
    {
        "author": "Almaca, C.",
        "year": 1989,
         "title": "Competition, available space, and speciation in Mediterranean crabs.", 
         "pub": "Monitore Zoologico Italiano,",
         "locale": "22(4): 477-486"
    },
    {
        "author": "Almaca, C.",
        "year": 1989,
         "title": "Biogeographic notes on the Mediterranean Brachyura.", 
         "pub": "Crustaceana,",
         "locale": "56(1): 14-17"
    },
    {
        "author": "Almaca, C.",
        "year": 1989,
         "title": "Documentos do Arquivo histórico do Museu Bocage relativos à exploração históriconatural angolana do Dr. Frederico Welwitsch (Agosto de 1853-Dezembro de 1860).", 
         "pub": "Arquivos do Museu Bocage, Nova Série,",
         "locale": "1(22): 335-347"
    },
    {
        "author": "Almaca, C.",
        "year": 1989,
         "title": "On the biology of northeastern Portuguese populations of Austropotamobius pallipes (Lereboullet, 1858).", 
         "pub": "Arquivos do Museu Bocage, Nova Série,",
         "locale": " 1(29): 419-428"
    },
    {
        "author": "Almaca, C.",
        "year": 1989,
         "title": "As colecções de conchas em gabinetes e museus de história natural portugueses.", 
         "pub": "Açoreana,",
         "locale": "7(1): 17-24"
    },
    {
        "author": "Almaca, C.",
        "year": 1989,
         "title": "Book review: The handling of chromosomes revisited.", 
         "pub": "Genetica,",
         "locale": "79(3): 223-231"
    },
    {
        "author": "Almaca, C.",
        "year": 1990,
         "title": "Structure and interactions in the crab community inhabiting Sabelariid worm colonies at Praia de Ribeira d’Ilhas (Ericeira, Portugal).", 
         "pub": "Arquivos do Museu Bocage, Nova Série,",
         "locale": "1(37): 505-519"
    },
    {
        "author": "Almaca, C.",
        "year": 1990,
         "title": "Neogene circum-Mediterranean paleogeography and Euro-Mediterranean Barbus biogeography.", 
         "pub": "Arquivos do Museu Bocage, Nova Série,",
         "locale": "1(41): 585-611"
    },
    {
        "author": "Almaca, C.",
        "year": 1990,
         "title": "A lampreia e o esturjão na bacia do Douro.", 
         "pub": "Observatório,",
         "locale": "1: 377-382"
    },
    {
        "author": "Almaca, C.",
        "year": 1990,
         "title": "Recursos animais e sua conservação: as populações portuguesas do lagostim-derio, Astacus pallipes Lereboullet, 1858.", 
         "pub": "Publicações Avulsas do Museu Bocage, Lisboa.",
         "locale": "22 pp"
    },
    {
        "author": "Almaca, C.",
        "year": 1990,
         "title": "Watercolours of Atlantic fishes of Joaquim José da Silva’s expedition to Angola (1783-1808).", 
         "pub": "Museu de Ciência da Universidade de Lisboa, Lisboa,",
         "locale": "4 pp"
    },
    {
        "author": "Almaca, C.",
        "year": 1990,
         "title": "Introdução.", 
         "pub": "In: Acta do Seminário: Portugal e a Legislação Comunitária sobre Protecção da Natureza. Sesimbra:",
         "locale": "9-13"
    },
    {
        "author": "Almaca, C.",
        "year": 1991,
         "title": "The beginning of the Portuguese mammalogy", 
         "pub": "Publicações Avulsas do Museu Bocage, Lisboa.",
         "locale": "58 pp"
    },
    {
        "author": "Almaca, C.",
        "year": 1991,
         "title": "As classificações zoológicas: aspectos históricos.", 
         "pub": "Publicações Avulsas do Museu Bocage, Lisboa.",
         "locale": "52 pp"
    },
    {
        "author": "Almaca, C.",
        "year": 1991,
         "title": "Evolutionary, biogeographical, and taxonomic remarks on Mesopotamian species of Barbus s.s..", 
         "pub": "Arquivos do Museu Bocage, Nova Série,",
         "locale": "2(4): 63-78"
    },
    {
        "author": "Almaca, C.",
        "year": 1991,
         "title": "Os portugueses e o conhecimento das faunas exóticas.", 
         "pub": "Oceanos,",
         "locale": "6: 52-63"
    },
    {
        "author": "Almaca, C.",
        "year": 1991,
         "title": "Frei Cristóvão de Lisboa e a zoologia brasileira.", 
         "pub": "Oceanos,",
         "locale": "6: 64-65"
    },
    {
        "author": "Almaca, C.",
        "year": 1991,
         "title": "L’ecrevisse a pieds blancs, Astacus pallipes Lereboullet 1858, au Portugal.", 
         "pub": "L’Astaciculteur de France,",
         "locale": "28: 11-16"
    },
    {
        "author": "Almaca, C.",
        "year": 1991,
         "title": "A conservação da Ria de Alvor.", 
         "pub": "Ciência e Natureza,",
         "locale": "1: 39-44"
    },
    {
        "author": "ALMAÇA, C. & CORTES, P.A.",
        "year": 1991,
         "title": "On the European brook lamprey, Lampetra planeri (Bloch, 1784) (Petromyzontidae), in Portugal.", 
         "pub": "Cybium",
         "locale": "15(3): 189-192"
    },
    {
        "author": "ALMAÇA, C. & CORTES, P.A.",
        "year": 1992,
         "title": "A tentative key to the species of Euro-Mediterranean Barbus (Cyprinidae, Pisces).", 
         "pub": "Garcia de Orta, série zoologica, Lisboa,",
         "locale": "16(1-2): 25-30"
    },
    {
        "author": "ALMAÇA, C.",
        "year": 1992,
         "title": "Notes on Capra pyrenaica lusitanica Schlegel, 1872. ", 
         "pub": "Mammalia,",
         "locale": "56(1): 121-124"
    },
    {
        "author": "ALMAÇA, C.",
        "year": 1992,
         "title": "Name, authorship, type specimen, and type locality of the Iberian Lynx.", 
         "pub": "Mammalia,",
         "locale": "56(4): 659-662"
    },
    {
        "author": "ALMAÇA, C.",
        "year": 1992,
         "title": "A evolução. Perspectiva histórica e filosófica.", 
         "pub": "Ingenium, Seminario de Estudos Galegos,",
         "locale": "3: 75-95"
    },
    {
        "author": "ALMAÇA, C.",
        "year": 1992,
         "title": "As primeiras fases da obra científica do Prof. J. A. Serra.", 
         "pub": "Brotéria Genética,",
         "locale": "13: 33-40"
    },
    {
        "author": "ALMAÇA, C.",
        "year": 1992,
         "title": "A expedição filosófica de Alexandre Rodrigues Ferreira, no contexto histórico-natural da sua época.", 
         "pub": "In: Viagem Filosófica de Alexandre Rodrigues Ferreira. Academia de Marinha. Lisboa:",
         "locale": "3-15"
    },
    {
        "author": "ALMAÇA, C.",
        "year": 1992,
         "title": "On the Portuguese population of Microtus agrestis (Linnaeus, 1761).", 
         "pub": "Arquivos do Museu Bocage, Nova Série,",
         "locale": "2(17): 319-335"
    },
    {
        "author": "ALMAÇA, C.",
        "year": 1992,
         "title": "Alexandre Rodrigues Ferreira e a exploração histórico-natural do Brasil.", 
         "pub": "Oceanos,",
         "locale": "9: 54-57"
    },
    {
        "author": "ALMAÇA, C., DOMINGUES, A. & FARIA, M.",
        "year": 1992,
         "title": "Viagem filosófica de Alexandre Rodrigues Ferreira.", 
         "pub": "Ciclo de Conferências. Academia de Marinha. Lisboa.",
         "locale": ""
    },
    {
        "author": "ALMAÇA, C.",
        "year": 1993,
         "title": "Bosquejo histórico da zoologia em Portugal.", 
         "pub": "Publicações Avulsas do Museu Bocage, Lisboa.",
         "locale": "50 pp"
    },
    {
        "author": "ALMAÇA, C.",
        "year": 1993,
         "title": "Evolutionism in Portugal.", 
         "pub": "Publicações Avulsas do Museu Bocage, Lisboa.",
         "locale": "30 pp"
    },
    {
        "author": "ALMAÇA, C.",
        "year": 1993,
         "title": "Os portugueses do Brasil e a Zoologia pré-lineana.", 
         "pub": "In: V.M. Soares et al. (eds.). A Universidade e os Descobrimentos. Imprensa Nacional-Casa da Moeda, Lisboa:",
         "locale": "175-193"
    },
    {
        "author": "ALMAÇA, C.",
        "year": 1993,
         "title": "The beginning of Portuguese carcinology.", 
         "pub": "In: F. Truesdale (ed.). History of Carcinology. Balkema, Rotterdam. Crustacean Issues,",
         "locale": "8: 31-39"
    },
    {
        "author": "ALMAÇA, C.",
        "year": 1993,
         "title": "Problems of conservation of Galemys pyrenaicus in Portugal.", 
         "pub": "Proceeding of the meeting on the Pyrenean Desman, Lisboa:",
         "locale": "9-10"
    },
    {
        "author": "ALMAÇA, C., DOMINGUES, A. & FARIA, M.",
        "year": 1993,
         "title": "Viagem filosófica de Alexandre Rodrigues Ferreira.", 
         "pub": "Academia de Marinha. Lisboa.",
         "locale": ""
    },
    {
        "author": "ALMAÇA, C.",
        "year": 1994,
         "title": "Evolutionism.", 
         "pub": "Publicações Avulsas do Museu Bocage, Lisboa.",
         "locale": "23 pp"
    },
    {
        "author": "ALMAÇA, C.",
        "year": 1994,
         "title": "Evolutionism and Mendelism.", 
         "pub": "Publicações Avulsas do Museu Bocage, Lisboa.",
         "locale": "35 pp"
    },
    {
        "author": "ALMAÇA, C.",
        "year": 1994,
        "title": "Studies on the taxonomy, biogeography, and speciation in Euro-Mediterranean Barbus (Barbus s.s.).", 
        "pub": "Arquivos do Museu Bocage, Nova Série,",
        "locale": "2(28): 455-462"
    },
    {
        "author": "ALMAÇA, C.",
        "year": 1994,
        "title": "O Professor Germano da Fonseca Sacarrão. Aspectos da sua obra científica e didáctica.", 
        "pub": "In: Professor Germano da Fonseca Sacarrão (1914- 1992). Museu Nacional de História Natural, Museu Bocage, Lisboa:",
        "locale": "5-22"
    },
    {
        "author": "ALMAÇA, C.",
        "year": 1995,
        "title": "Freshwater fish and their conservation in Portugal.", 
        "pub": "Biological Conservation,",
        "locale": "72(2): 125-127"
    },
    {
        "author": "ALMAÇA, C.",
        "year": 1995,
        "title": "Fish species and varieties introduced into Portuguese inland waters.", 
        "pub": "Publicações Avulsas do Museu Bocage, Lisboa.",
        "locale": "29 pp"
    },
    {
        "author": "ALMAÇA, C.",
        "year": 1995,
        "title": "Uma controvérsia antropológica de 1881: Oliveira Martins e Eduardo Burnay.", 
        "pub": "Publicações Avulsas do Museu Bocage, Lisboa.",
        "locale": "22 pp"
    },
    {
        "author": "ALMAÇA, C.",
        "year": 1995,
        "title": "A Critical review of the work by A. Guerra, 1992. Mollusca, Cephalopoda.", 
        "pub": "Boletim do Instituto Português de Investigação Marítima,",
        "locale": "1: 105-107"
    },
    {
        "author": "ALMAÇA, C.",
        "year": 1995,
        "title": "Peixes dos rios de Portugal.", 
        "pub": "Edições Inapa, Lisboa.",
        "locale": "129 pp"
    },
    {
        "author": "ALMAÇA, C.",
        "year": 1996,
        "title": "Ciríaco, um negro pigarço do século XVIII.", 
        "pub": "Publicações Avulsas do Museu Bocage, Lisboa.",
        "locale": "18 pp"
    },
    {
        "author": "ALMAÇA, C.",
        "year": 1996,
        "title": "A natural history museum of the 18th century: the Royal Museum and Botanical Garden of Ajuda.", 
        "pub": "Publicações Avulsas do Museu Bocage, Lisboa.",
        "locale": "28 pp"
    },
    {
        "author": "ALMAÇA, C.",
        "year": 1996,
        "title": "Augusto Nobre e a Zoologia portuguesa.", 
        "pub": "Publicações do Instituto de Zoologia “Dr. Augusto Nobre”, Faculdade de Ciências do Porto,",
        "locale": "234: 1-22"
    },
    {
        "author": "ALMAÇA, C.",
        "year": 1996,
        "title": "The beginning of Portuguesa mammalogy.", 
        "pub": "In: M.D. Mathias, M. Santos-Reis, G. Amori, R. Libois, A. Mitchell-Jones & M.C. Saint-Girons (eds.). European Mammals. Proceedings of the I European Congress of Mammalogy. Museu Nacional de História Natural, Museu Bocage, Lisboa:",
        "locale": "37-46"
    },
    {
        "author": "ALMAÇA, C.",
        "year": 1997,
        "title": "Falconers: the first Portuguese naturalists.", 
        "pub": "Archives of Natural History, London,",
        "locale": "24(2): 175-187"
    },
    {
        "author": "ALMAÇA, C.",
        "year": 1997,
        "title": "Augusto Nobre and marine biology in Portugal.", 
        "pub": "In: L. Saldanha & P. Ré (eds.). One Hundred Years of Portuguese Oceanography. Publicações Avulsas do Museu Bocage, 2ª série,",
        "locale": "2: 125-134"
    },
    {
        "author": "ALMAÇA, C.",
        "year": 1997,
        "title": "Early evolutionism in Portugal.", 
        "pub": "Publicações Avulsas do Museu Bocage, 2ª série,",
        "locale": "1: 1-22"
    },
    {
        "author": "ALMAÇA, C.",
        "year": 1997,
        "title": "Lamarck et l’évolutionnisme au Portugal.", 
        "pub": "Actes du 119ème Congrès National des Sociétés Historiques et Scientifiques, Amiens:",
        "locale": "689-693"
    },
    {
        "author": "ALMAÇA, C. (compil.)",
        "year": 1997,
        "title": "Professor Germano da Fonseca Sacarrão (1914-1992).", 
        "pub": "Museu e Laboratório Zoológico e Antropológico (Museu Bocage). Lisboa.",
        "locale": "383 pp"
    },
    {
        "author": "ALMAÇA, C.",
        "year": 1998,
        "title": "Baleias, focas e peixes-bois na história natural portuguesa.", 
        "pub": " Museu Bocage. Lisboa.",
        "locale": "105 pp"
    },
    {
        "author": "ALMAÇA, C.",
        "year": 1998,
        "title": "A Tenca, Tinca tinca (Linnaeus, 1758), é ou não uma Espécie Introducida en Portugal? ", 
        "pub": "Publicaciones de la Cámara de Comercio e Industria de Cáceres,",
        "locale": "63: 277-283"
    },
    {
        "author": "ALMAÇA, C.",
        "year": 1998,
        "title": "Para melhor apreciar a galeria de zoologia: Museu Bocage / Museu Nacional de História Natural. Vol. 1.", 
        "pub": "Ecosistemas. Museu Bocage, Lisboa.",
        "locale": "8 pp"
    },
    {
        "author": "ALMAÇA, C.",
        "year": 1998,
        "title": "Para melhor apreciar a galeria de zoologia: Museu Bocage / Museu Nacional de História Natural. Vol. 2.", 
        "pub": "Ecótonos. Museu Bocage, Lisboa.",
        "locale": "26 pp"
    },
    {
        "author": "ALMAÇA, C., COLLARES-PEREIRA, M.J. & COELHO, M.M.",
        "year": 1998,
        "title": "Relatório do estudo da fauna ictiológica do Rio Tejo.", 
        "pub": "Projecto radioecologia do Rio Tejo, LNETI.",
        "locale": "19 pp"
    },
    {
        "author": "ALMAÇA, C.",
        "year": 1999,
        "title": "Reptéis e alimentaçao no Brasil colonial.", 
        "pub": "Publicaciones de la Cámara de Comercio e Industria de Cáceres,",
        "locale": "71"
    },
    {
        "author": "ALMAÇA, C.",
        "year": 1999,
        "title": "O Darwinismo na universidade portuguesa (1865-1890).", 
        "pub": "Museu Bocage, Museu Nacional de História Natural, Lisboa.",
        "locale": "118 pp"
    },
    {
        "author": "ALMAÇA, C.",
        "year": 2000,
        "title": "O homem medieval e a biodiversidade.", 
        "pub": "Museu Bocage, Museu Nacional de História Natural, Lisboa.",
        "locale": "196 pp"
    },
    {
        "author": "ALMAÇA, C.",
        "year": 2000,
        "title": "Neo-Lamarckism in Portugal.", 
        "pub": "Asclepio,",
        "locale": "52(2): 85-98"
    },
    {
        "author": "ALMAÇA, C.",
        "year": 2000,
        "title": "Iguaraguás, hipupiáras, baleias e âmbar: os portugueses e a natureza brasileira.", 
        "pub": "Atalaia,",
        "locale": "6-7: 217-222"
    },
    {
        "author": "ALMAÇA, C.",
        "year": 2000,
        "title": "Museu Bocage: ensino e exibição.", 
        "pub": "Museu Bocage, Museu Nacional de História Natural, Lisboa.",
        "locale": "76 pp"
    },
    {
        "author": "ALMAÇA, C. & ELVIRA, B.",
        "year": 2000,
        "title": "Past and present distribution of Acipenser sturio L., 1758 on the Iberian Peninsula.", 
        "pub": "Boletín. Instituto Español de Oceanografía",
        "locale": "16(1-4): 11-16"
    },
    {
        "author": "ALMAÇA, C.",
        "year": 2001,
        "title": "Naturalistas del siglo XIX. Relaciones entre Víctor López Seoane y el Museo Bocage de Lisboa.", 
        "pub": "Ingenium (Sada),",
        "locale": "7: 25-34"
    },
    {
        "author": "ALMAÇA, C.",
        "year": 2001,
        "title": "A biodiversidade exótica e os criacionismos.", 
        "pub": "Atalaia,",
        "locale": "8-9: 131-140"
    },
    {
        "author": "ALMAÇA, C.",
        "year": 2001,
        "title": "Artur Ricardo Jorge.", 
        "pub": "In: Memórias de Professores Cientistas da Faculdade de Ciências da Universidade de Lisboa, 1911-2001. Edição da Faculdade de Ciências da Universidade de Lisboa. Lisboa.",
        "locale": ""
    },
    {
        "author": "ALMAÇA, C.",
        "year": 2002,
        "title": "Reino Animal.", 
        "pub": "Episteme,",
        "locale": "15: 97-106"
    },
    {
        "author": "ALMAÇA, C.",
        "year": 2002,
        "title": "A zoologia pré-lineana no Brasil.", 
        "pub": "Museu Bocage, Museu Nacional de História Natural, Lisboa.",
        "locale": "148 pp"
    },
    {
        "author": "ALMAÇA, C.",
        "year": 2002,
        "title": "Introdução.", 
        "pub": " In: Viagem ao Brasil de Alexandre Rodrigues Ferreira. Vol. 1. Kapa Editorial. Lisboa.",
        "locale": ""
    },
    {
        "author": "ALMAÇA, C.",
        "year": 2002,
        "title": "Darwinism in Portugal: teaching, research and dissemination following the Republican University Reforms (1911).", 
        "pub": "In: Evolucionismo y cultura: darwinismo en Europa e Iberoamérica. Ediciones Doce Calles. Aranjuez, Madrid:",
        "locale": "199-212"
    },
    {
        "author": "ALMAÇA, C.",
        "year": 2002,
        "title": "Natural history and applications in the “philosophical expedition” of Alexandre Rodrigues Ferreira to Amazonia and the Mato Grosso (1783- 1792).", 
        "pub": "In: G. Laurent (ed.). Earth sciences, geography and cartography. Brepols, Bélgica:",
        "locale": "8-17"
    },
    {
        "author": "ALMAÇA, C.",
        "year": 2003,
        "title": "Barbus microcephalus Almaça, 1967",  
        "pub": "In: P.M. Banarescu & N.G. Bogutskaya (eds.). The Freshwater Fishes of Europe. Cyprinidae 2. Part II. Barbus. AULA-Verlag, Wiesbaden",
        "locale": "287-292"
    },
    {
        "author": "ALMAÇA, C. & BANARESCU, P.M.",
        "year": 2003,
        "title": "Barbus bocagei Steindachner, 1865. In: P.M. Banarescu & N.G. Bogutskaya (eds.).",  
        "pub": "The Freshwater Fishes of Europe. Cyprinidae 2. Part II. Barbus. AULAVerlag, Wiesbaden:",
        "locale": "99-112"
    },
    {
        "author": "ALMAÇA, C. & BANARESCU, P.M.",
        "year": 2003,
        "title": "Barbus comizo Steindachner, 1865. In: P.M. Banarescu & N.G. Bogutskaya (eds.).",  
        "pub": "The Freshwater Fishes of Europe. Cyprinidae 2. Part II. Barbus. AULAVerlag, Wiesbaden:",
        "locale": "173-180"
    },
    {
        "author": "ALMAÇA, C. & BANARESCU, P.M.",
        "year": 2003,
        "title": "Barbus graellsii Steindachner, 1866. In: P.M. Banarescu & N.G. Bogutskaya (eds.).",  
        "pub": "The Freshwater Fishes of Europe. Cyprinidae 2. Part II. Barbus. AULAVerlag, Wiesbaden:",
        "locale": "227-234"
    },
    {
        "author": "ALMAÇA, C. & BANARESCU, P.M.",
        "year": 2003,
        "title": "Barbus sclateri Steindachner, 1868. In: P.M. Banarescu & N.G. Bogutskaya (eds.).",  
        "pub": "The Freshwater Fishes of Europe. Cyprinidae 2. Part II. Barbus. AULAVerlag, Wiesbaden:",
        "locale": "377-387"
    },
    {
        "author": "ALMAÇA, C. & BANARESCU, P.M.",
        "year": 2003,
        "title": "Barbus steindachneri Almaça, 1967. In: P.M. Banarescu & N.G. Bogutskaya (eds.).",  
        "pub": "The Freshwater Fishes of Europe. Cyprinidae 2. Part II. Barbus. AULAVerlag, Wiesbaden:",
        "locale": "389-395"
    },
    {
        "author": "BOGUTSKAYA, N.G., BANARESCU, P.M. & ALMAÇA, C.",
        "year": 2003,
        "title": "Barbus capito (Gueldenstaedt, 1773). In: P.M. Banarescu & N.G. Bogutskaya (eds.).",  
        "pub": "The Freshwater Fishes of Europe. Cyprinidae 2. Part II. Barbus. AULAVerlag, Wiesbaden:",
        "locale": "147-162"
    },
    {
        "author": "BOGUTSKAYA, N.G., BANARESCU, P.M. & ALMAÇA, C.",
        "year": 2003,
        "title": "arbus mursa (Gueldenstaedt, 1773). In: P.M. Banarescu & N.G. Bogutskaya (eds.).",  
        "pub": "The Freshwater Fishes of Europe. Cyprinidae 2. Part II. Barbus. AULAVerlag, Wiesbaden:",
        "locale": "293-300"
    },
    {
        "author": "ALMAÇA, C.",
        "year": 2004,
        "title": "Saber ictiológico e suas aplicações em Portugal (época pré-lineana).", 
        "pub": "Boletim da Sociedade de Geografia de Lisboa,:",
        "locale": "122: 145-159"
    },
    {
        "author": "ALMAÇA, C.",
        "year": 2005,
        "title": "Revisitamos Lamarck. Atendência para o progresso.", 
        "pub": "Actas do Colóquio Teilhard de Chardin. FCSHUN. Lisboa:",
        "locale": "41-45"
    },
    {
        "author": "ALMAÇA, C.",
        "year": 2005,
        "title": "Albert Monard e o Museu Bocage.", 
        "pub": "Publicações Avulsas do Museu Bocage, 2ª série,",
        "locale": "9: 1-23"
    },
    {
        "author": "ALMAÇA, C., MATOS, M. & OOM, M.M.",
        "year": 2005,
        "title": "A conservação ex situ e a restauração de espécies extintas.", 
        "pub": "Revista de Biologia,",
        "locale": "23(1-4): 7-21"
    },
    {
        "author": "ALMAÇA, C. (rev.cientifica)",
        "year": 2006,
        "title": "Obras Completas de Aristóteles. História dos Animais I. Livros I-VI de Aristóteles.", 
        "pub": " Biblioteca de Autores Clássicos. Imprensa Nacional Casa da Moeda. Lisboa:",
        "locale": "326 pp"
    },
    {
        "author": "ALMAÇA, C.",
        "year": 2006,
        "title": "O elogio da diferença. In: A. Tostões, E.R. Arantes e Oliveira, J.M. Pinto Paixão & P. Magalhães (eds.).", 
        "pub": "Encontro de Saberes. Fundação Calouste Gulbenkian. Lisboa:",
        "locale": "31-49"
    },
    {
        "author": "ALMAÇA, C.",
        "year": 2007,
        "title": "Dois séculos de evolucionismo.", 
        "pub": "In: A. Soares (coord.). Biologias na noite. Edições Afrontamento. Porto:",
        "locale": "26-42"
    },
    {
        "author": "ALMAÇA, C.",
        "year": 2007,
        "title": "100 anos da Sociedade Portuguesa de Ciências Naturais.", 
        "pub": "In: Biodiversidade - 100 anos da Sociedade Portuguesa de Ciências Naturais. Sociedade Portuguesa de Ciências Naturais. Lisboa:",
        "locale": "7-10"
    },
    {
        "author": "ALMAÇA, C. (rev.cientifica)",
        "year": 2008,
        "title": "Obras Completas de Aristóteles. História dos Animais II. Livros VII-X de Aristóteles.", 
        "pub": "Biblioteca de Autores Clássicos. Imprensa Nacional Casa da Moeda. Lisboa:",
        "locale": "280 pp"
    },
    {
        "author": "ALMAÇA, C.",
        "year": 2008,
        "title": "As contradições do criacionismo.", 
        "pub": "In: Evolução: História e argumentos. Esfera do Caos. Lisboa:",
        "locale": "43-51"
    },
    {
        "author": "ALMAÇA, C.",
        "year": 2008,
        "title": "Conservação da biodiversidade, ecologia e biogeografia.", 
        "pub": "Boletim da Sociedade de Geografia de Lisboa,",
        "locale": "126(1-12): 51-63"
    }
]